django_tagging-0.4.6.dist-info/DESCRIPTION.rst
django_tagging-0.4.6.dist-info/METADATA
django_tagging-0.4.6.dist-info/RECORD
django_tagging-0.4.6.dist-info/WHEEL
django_tagging-0.4.6.dist-info/metadata.json
django_tagging-0.4.6.dist-info/top_level.txt
tagging/__init__.py
tagging/admin.py
tagging/apps.py
tagging/fields.py
tagging/forms.py
tagging/generic.py
tagging/managers.py
tagging/models.py
tagging/registry.py
tagging/settings.py
tagging/utils.py
tagging/views.py
tagging/migrations/0001_initial.py
tagging/migrations/0002_on_delete.py
tagging/migrations/0003_adapt_max_tag_length.py
tagging/migrations/__init__.py
tagging/templatetags/__init__.py
tagging/templatetags/tagging_tags.py
tagging/tests/__init__.py
tagging/tests/models.py
tagging/tests/settings.py
tagging/tests/tags.txt
tagging/tests/tests.py
tagging/tests/urls.py
tagging/tests/utils.py
