Metadata-Version: 1.1
Name: django-tagging
Version: 0.4.6
Summary: Generic tagging application for Django
Home-page: https://github.com/Fantomas42/django-tagging
Author: Fantomas42
Author-email: fantomas42@gmail.com
License: BSD License
Keywords: django,tag,tagging
Platform: UNKNOWN
Classifier: Framework :: Django
Classifier: Environment :: Web Environment
Classifier: Operating System :: OS Independent
Classifier: Development Status :: 5 - Production/Stable
Classifier: Intended Audience :: Developers
Classifier: License :: OSI Approved :: BSD License
Classifier: Programming Language :: Python
Classifier: Programming Language :: Python :: 2
Classifier: Programming Language :: Python :: 2.7
Classifier: Programming Language :: Python :: 3
Classifier: Topic :: Utilities
Classifier: Topic :: Software Development :: Libraries :: Python Modules
